catminer/__init__.py
catminer/__main__.py
catminer/catminer.py
catminer/config/settings.ini
catminer-1.5.dist-info/LICENSE
catminer-1.5.dist-info/METADATA
catminer-1.5.dist-info/WHEEL
catminer-1.5.dist-info/entry_points.txt
catminer-1.5.dist-info/top_level.txt
catminer-1.5.dist-info/RECORD
