Metadata-Version: 2.1
Name: catminer
Version: 1.5
Summary: Data-mining tool for .CAT* (CATIA) files.
Home-page: https://github.com/WWU-CAD-Autograder/catminer
Author: Jack Wilson
License: UNKNOWN
Platform: UNKNOWN
Classifier: Development Status :: 5 - Production/Stable
Classifier: Environment :: Win32 (MS Windows)
Classifier: License :: OSI Approved :: MIT License
Classifier: Natural Language :: English
Classifier: Operating System :: Microsoft :: Windows
Classifier: Programming Language :: Python :: 3
Requires-Python: >=3.7
Requires-Dist: pyvba
Requires-Dist: tqdm
